Metadata-Version: 2.4
Name: zzzzzzzzzzzzzzzzzzzzzzzzzzzzzzzzzzzzzzzzzzzzzzzzzzzzzzzzzzzzzzzzzzzzzzzzzzzzzzzzzzzzzzzzzzzzzzzzzzzzzzzzzzzzzzzzzzzzzzzzzzzzzzzzzzzzzzzzzzzzzzzzzzzzzzzzzzzzzzzzzzzzzzzzzzzzzzzzzzzzzzzzzzzz
Version: 0.1.0
Summary: The last package in pypi providing the last values of everything
Author-email: K0IN <thisk0in@gmail.com>
License: MIT License
Project-URL: Homepage, https://github.com/k0in/last
License-File: LICENSE
Requires-Dist: requests>=2.0
Dynamic: license-file
